MANIFEST.in
README.md
demo.py
pic.jpg
respack.py
setup.py
respack.egg-info/PKG-INFO
respack.egg-info/SOURCES.txt
respack.egg-info/dependency_links.txt
respack.egg-info/top_level.txt